Metadata-Version: 2.1
Name: pytorch-cgx
Version: 0.1.1
Summary: pytorch extension adding a backend supporting allreduce of quantized buffers.
Home-page: https://github.com/IST-DASLab/torch_cgx/
Author: Ilia Markov
Author-email: ilia.markov@ist.ac.at
License: UNKNOWN
Download-URL: https://github.com/IST-DASLab/torch_cgx/archive/refs/tags/v0.1.1.tar.gz
Platform: UNKNOWN
License-File: LICENSE.txt
